rlbot/__init__.py
rlbot/config.py
rlbot/interface.py
rlbot/py.typed
rlbot/version.py
rlbot/flat/__init__.py
rlbot/managers/__init__.py
rlbot/managers/bot.py
rlbot/managers/hivemind.py
rlbot/managers/match.py
rlbot/managers/rendering.py
rlbot/managers/script.py
rlbot/utils/__init__.py
rlbot/utils/gateway.py
rlbot/utils/logging.py
rlbot/utils/maps.py
rlbot/utils/os_detector.py
rlbot-2.0.0b49.dist-info/licenses/LICENSE
rlbot-2.0.0b49.dist-info/METADATA
rlbot-2.0.0b49.dist-info/WHEEL
rlbot-2.0.0b49.dist-info/top_level.txt
rlbot-2.0.0b49.dist-info/RECORD
