Metadata-Version: 2.4
Name: rlbot
Version: 2.0.0b49
Summary: A high performance Python interface for communicating with RLBot v5.
Author-email: RLBot Community <rlbotofficial@gmail.com>
License: MIT
Project-URL: Repository, https://github.com/RLBot/python-interface
Keywords: rocket-league
Requires-Python: >=3.11
License-File: LICENSE
Requires-Dist: rlbot_flatbuffers~=0.18.2
Requires-Dist: psutil==7.*
Dynamic: license-file
